fdce/get_coeff.py
fdce/__init__.py
fdce/derivate.py
fdce/_extension/__init__.py
fdce/_extension/_fdce.cpython-38-i386-linux-gnu.so
tests/test_derivate.py
tests/__init__.py
tests/test_get_coeff.py
fdce-0.1.1.dist-info/WHEEL
fdce-0.1.1.dist-info/top_level.txt
fdce-0.1.1.dist-info/LICENSE
fdce-0.1.1.dist-info/METADATA
fdce-0.1.1.dist-info/RECORD
