Metadata-Version: 2.1
Name: fdce
Version: 0.1.1
Summary: Finite difference coefficient estimator
Author: Jorge Morgado Vega
Author-email: jorge.morgadov@gmail.com
Requires: numpy
Requires-Python: >=3.8
License-File: LICENSE
